[
  {
    "id": 1,
    "title": "Login page error",
    "description": "Customer unable to login despite using correct credentials; reset password attempts fail repeatedly with no success.",
    "customer": "Rahim",
    "priority": "High",
    "status": "Open",
    "createdAt": "2026-03-01T10:15:00Z"
  },
  {
    "id": 2,
    "title": "Profile update not saving",
    "description": "Payment attempts keep failing due to card being declined, balance insufficient, or gateway timeout issues.",
    "customer": "Karim",
    "priority": "Medium",
    "status": "Pending",
    "createdAt": "2026-03-02T12:30:00Z"
  },
  {
    "id": 3,
    "title": "Payment gateway timeout",
    "description": "User cannot download January invoice from the billing section; download button shows error and file missing.",
    "customer": "Salma",
    "priority": "High",
    "status": "In-Progress",
    "createdAt": "2026-03-02T15:45:00Z"
  },
  {
    "id": 4,
    "title": "Dashboard stats incorrect",
    "description": "TDashboard statistics show incorrect data; order counts and revenue numbers are mismatched across different pages.",
    "customer": "Amina",
    "priority": "Low",
    "status": "Resolved",
    "createdAt": "2026-03-03T09:20:00Z"
  },
  {
    "id": 5,
    "title": "Email notifications not sent",
    "description": "Email notifications not being sent to customers after order confirmation or password reset requests fail.",
    "customer": "Jamil",
    "priority": "High",
    "status": "Pending",
    "createdAt": "2026-03-03T11:50:00Z"
  },
  {
    "id": 6,
    "title": "Search feature slow",
    "description": "Product search function is very slow; results take more than 10 seconds to display on the page.",
    "customer": "Farida",
    "priority": "Medium",
    "status": "In-Progress",
    "createdAt": "2026-03-04T08:10:00Z"
  },
  {
    "id": 7,
    "title": "Password reset link broken",
    "description": "Password reset link in emails is broken; users cannot reset their account passwords successfully online.",
    "customer": "Rahman",
    "priority": "High",
    "status": "Resolved",
    "createdAt": "2026-03-04T14:25:00Z"
  },
  {
    "id": 8,
    "title": "Mobile layout issues",
    "description": "Website layout breaks on mobile devices; buttons, images, and text overlap in small screen resolutions.",
    "customer": "Nabila",
    "priority": "Medium",
    "status": "Pending",
    "createdAt": "2026-03-05T09:00:00Z"
  },
  {
    "id": 9,
    "title": "Incorrect invoice amount",
    "description": "Invoices display wrong totals; some discounts or taxes are not applied correctly in customer billing.",
    "customer": "Hasan",
    "priority": "High",
    "status": "In-Progress",
    "createdAt": "2026-03-05T11:15:00Z"
  },
  {
    "id": 10,
    "title": "Slow image upload",
    "description": "Uploading images for products takes excessive time, sometimes failing to complete, frustrating the user.",
    "customer": "Rina",
    "priority": "Low",
    "status": "Pending",
    "createdAt": "2026-03-05T13:40:00Z"
  }
]